shoelace/__init__.py
shoelace/dataset.py
shoelace/evaluation.py
shoelace/iterator.py
shoelace/functions/__init__.py
shoelace/functions/logcumsumexp.py
shoelace/loss/__init__.py
shoelace/loss/listwise.py
shoelace/loss/pairwise.py
shoelace-0.2.1.dist-info/DESCRIPTION.rst
shoelace-0.2.1.dist-info/METADATA
shoelace-0.2.1.dist-info/RECORD
shoelace-0.2.1.dist-info/WHEEL
shoelace-0.2.1.dist-info/metadata.json
shoelace-0.2.1.dist-info/top_level.txt
test/__init__.py
test/test_dataset.py
test/test_evaluation.py
test/test_iterator.py
test/utils.py
test/examples/__init__.py
test/examples/test_linear_network.py
test/functions/__init__.py
test/functions/test_logcumsumexp.py
test/loss/__init__.py
test/loss/test_listwise.py
