Metadata-Version: 2.0
Name: shoelace
Version: 0.2.1
Summary: Neural Learning to Rank using Chainer
Home-page: https://github.com/rjagerman/shoelace
Author: Rolf Jagerman
Author-email: rjagerman@gmail.com
License: MIT
Download-URL: https://github.com/rjagerman/shoelace/archive/v0.2.1.tar.gz
Platform: UNKNOWN
Requires-Dist: chainer (>=2.0.0)
Requires-Dist: numpy (>=1.12.0)
